netgear_plus/__init__.py
netgear_plus/models.py
netgear_plus/netgear_crypt.py
netgear_plus-0.1.8.dist-info/METADATA
netgear_plus-0.1.8.dist-info/WHEEL
netgear_plus-0.1.8.dist-info/entry_points.txt
netgear_plus-0.1.8.dist-info/licenses/LICENSE.md
netgear_plus-0.1.8.dist-info/RECORD
