Metadata-Version: 2.3
Name: netgear-plus
Version: 0.1.8
Summary: A library for interacting with Netgear Plus switches.
Project-URL: Homepage, https://github.com/foxey/py-netgear-plus
Project-URL: Issues, https://github.com/foxey/py-netgear-plus/issues
Author-email: Michiel Fokke <github@fokke.org>, Christian Karrié <ckarrie@gmail.com>
License-File: LICENSE.md
Keywords: api,library,netgear,plus,switch
Classifier: License :: OSI Approved :: Apache Software License
Classifier: Operating System :: OS Independent
Classifier: Programming Language :: Python :: 3
Requires-Python: >=3.8
Requires-Dist: lxml
Requires-Dist: requests
